{
  "id": "4f736d1c761721c1",
  "path": "Documentos en Servidor Atlántica/1950801-LIS-6500-00_Lista de Consumidores Eléctricos.pdf",
  "top_dir": "Documentos en Servidor Atlántica",
  "ext": "pdf",
  "size_bytes": 288143,
  "size_human": "281 KB",
  "mtime_iso": "2026-06-08T16:14:00.000Z",
  "title": "1950801-LIS-6500-00 Lista de Consumidores Eléctricos",
  "doc_code": null,
  "revision": null,
  "status": "ok",
  "text_chars": 6881,
  "token_estimate": 1720,
  "chunks": 5,
  "card_path": ".yeyo-memory/cards/4f736d1c761721c1.json",
  "extracted_path": ".yeyo-memory/extracted/4f736d1c761721c1.txt",
  "metadata": {
    "pages": 3,
    "pdf_metadata": {
      "Author": "asieraurrekoetxea",
      "CreationDate": "D:20260324182509+01'00'",
      "Creator": "PScript5.dll Version 5.2.2",
      "ModDate": "D:20260324182509+01'00'",
      "Producer": "Acrobat Distiller 17.0 (Windows)",
      "Title": ""
    },
    "encrypted": false
  },
  "processed_at": "2026-06-08T18:27:45.640592+00:00"
}
