{
  "id": "6b0dab6948c3c1a0",
  "path": "Helios Sole/Helios I/5.9 BT/5.9.2 Pozo 1/5.9.2.8 Presentacion anexo erratas.pdf",
  "top_dir": "Helios Sole",
  "ext": "pdf",
  "size_bytes": 68003,
  "size_human": "66 KB",
  "mtime_iso": "2026-06-08T16:18:00.000Z",
  "title": "5.9.2.8 Presentacion anexo erratas",
  "doc_code": null,
  "revision": null,
  "status": "needs_ocr_or_empty",
  "text_chars": 0,
  "token_estimate": 0,
  "chunks": 0,
  "card_path": ".yeyo-memory/cards/6b0dab6948c3c1a0.json",
  "extracted_path": null,
  "metadata": {
    "pages": 1,
    "pdf_metadata": {
      "Creator": "Canon iR2525",
      "CreationDate": "D:20120514151021+01'00'",
      "Producer": "Canon iR2525"
    },
    "encrypted": false,
    "ai_features": {
      "source_corpus": "Proyecto Helios Sole",
      "project_area": "Helios I",
      "deliverable_part": "Documentacion auxiliar",
      "discipline": "Electrica",
      "extraction_quality": "requiere_ocr",
      "ai_action": "ocr_local_si_es_relevante",
      "reuse_priority": "pendiente_ocr",
      "page_count": 1,
      "indexed_reference_count": 0,
      "enriched_at": "2026-06-08T18:48:59.739698+00:00"
    }
  },
  "processed_at": "2026-06-08T18:38:31.120367+00:00"
}
