{
  "id": "b83ef6e091fcceb0",
  "path": "13_Documentos de Inspección Final/S3.1  04_04_2018.pdf",
  "top_dir": "13_Documentos de Inspección Final",
  "ext": "pdf",
  "size_bytes": 1158103,
  "size_human": "1.1 MB",
  "mtime_iso": "2026-06-05T06:27:00.000Z",
  "title": "S3.1 04 04 2018",
  "doc_code": null,
  "revision": null,
  "status": "ok",
  "text_chars": 10479,
  "token_estimate": 2619,
  "chunks": 7,
  "card_path": ".yeyo-memory/cards/b83ef6e091fcceb0.json",
  "extracted_path": ".yeyo-memory/extracted/b83ef6e091fcceb0.txt",
  "metadata": {
    "pages": 1,
    "pdf_metadata": {
      "Author": "Eng Department",
      "CreationDate": "D:20180404160925-05'00'",
      "Creator": "AutoCAD 2017 - English 2017 (21.0s (LMS Tech))",
      "ModDate": "D:20180404161056-05'00'",
      "Producer": "Acrobat Distiller 18.0 (Windows)",
      "Title": "S3.1"
    },
    "encrypted": true,
    "empty_password_decrypt_result": "1",
    "ai_features": {
      "source_corpus": "Repositorio Solana / Yeyo",
      "project_area": "General",
      "deliverable_part": "Planos",
      "discipline": "General",
      "extraction_quality": "alta_texto_extraido",
      "ai_action": "usar_chunks",
      "reuse_priority": "media",
      "page_count": 1,
      "indexed_reference_count": 0,
      "enriched_at": "2026-06-08T20:00:39.318696+00:00"
    },
    "plan_tag": {
      "kind": "Layout / distribucion general",
      "mode": "tag_only_no_ocr",
      "tagged_at": "2026-06-08T19:58:17.152878+00:00",
      "local_only": true
    }
  },
  "processed_at": "2026-06-08T19:58:17.152880+00:00"
}
