{
  "id": "fe98b101f2adb0c7",
  "path": "04 GD Fabricacon LOI TES 3/Lista documentos/1950201 Document List.pdf",
  "top_dir": "04 GD Fabricacon LOI TES 3",
  "ext": "pdf",
  "size_bytes": 79757,
  "size_human": "78 KB",
  "mtime_iso": "2026-06-05T06:19:00.000Z",
  "title": "1950201 Document List",
  "doc_code": null,
  "revision": null,
  "status": "ok",
  "text_chars": 2662,
  "token_estimate": 665,
  "chunks": 2,
  "card_path": ".yeyo-memory/cards/fe98b101f2adb0c7.json",
  "extracted_path": ".yeyo-memory/extracted/fe98b101f2adb0c7.txt",
  "metadata": {
    "pages": 1,
    "pdf_metadata": {
      "Author": "Alvaro Bilbao",
      "CreationDate": "D:20191029143235+01'00'",
      "Creator": "Acrobat PDFMaker 17 para Excel",
      "ModDate": "D:20191029143237+01'00'",
      "Producer": "Adobe PDF Library 15.0"
    },
    "encrypted": false,
    "ai_features": {
      "source_corpus": "Repositorio Solana / Yeyo",
      "project_area": "TES / almacenamiento",
      "deliverable_part": "Listados e indices",
      "discipline": "Proceso / mecanica / tuberias",
      "extraction_quality": "alta_texto_extraido",
      "ai_action": "usar_chunks",
      "reuse_priority": "media",
      "page_count": 1,
      "indexed_reference_count": 0,
      "enriched_at": "2026-06-08T20:00:39.318696+00:00"
    }
  },
  "processed_at": "2026-06-05T09:14:29.497154+00:00"
}
